{
  "projectId": "infra-nucleus-hjlsj",
  "appId": "1:1077507948571:web:21cb68619a08ef33d478be",
  "apiKey": "AIzaSyAJ8rn5mmIo8OPBsHA7aRehI4k9CvCNviA",
  "authDomain": "infra-nucleus-hjlsj.firebaseapp.com",
  "firestoreDatabaseId": "ai-studio-remixremixremixr-ecab5233-0c6a-4d30-9cf9-57f20089dab4",
  "storageBucket": "infra-nucleus-hjlsj.firebasestorage.app",
  "messagingSenderId": "1077507948571",
  "measurementId": "",
  "oAuthClientId": "1077507948571-ve7i29rscmab7d36hqbaf07ikd65sd45.apps.googleusercontent.com"
}